Metadata-Version: 1.1
Name: EshaanBasicCalculator
Version: 0.0.1
Summary: A BASIC CALCULATOR
Home-page: UNKNOWN
Author: Eshaan Gupta
Author-email: UNKNOWN
License: MIT
Keywords: Calculator
Platform: UNKNOWN
Classifier: Development Status :: 5 - Production/Stable
Classifier: Intended Audience :: Education
Classifier: Operating System :: Microsoft :: Windows :: Windows 10
Classifier: License :: OSI Approved :: MIT License
Classifier: Programming Language :: Python :: 3
